transactions/__init__.py
transactions/common/__init__.py
transactions/common/crypto.py
transactions/common/exceptions.py
transactions/common/input.py
transactions/common/memoize.py
transactions/common/output.py
transactions/common/schema/README.md
transactions/common/schema/__init__.py
transactions/common/schema/v1.0/transaction.yaml
transactions/common/schema/v1.0/transaction_create.yaml
transactions/common/schema/v1.0/transaction_transfer.yaml
transactions/common/schema/v2.0/transaction.yaml
transactions/common/schema/v2.0/transaction_chain_migration_election.yaml
transactions/common/schema/v2.0/transaction_create.yaml
transactions/common/schema/v2.0/transaction_transfer.yaml
transactions/common/schema/v2.0/transaction_validator_election.yaml
transactions/common/schema/v2.0/transaction_vote.yaml
transactions/common/schema/v3.0/transaction.yaml
transactions/common/schema/v3.0/transaction_chain_migration_election.yaml
transactions/common/schema/v3.0/transaction_compose.yaml
transactions/common/schema/v3.0/transaction_create.yaml
transactions/common/schema/v3.0/transaction_decompose.yaml
transactions/common/schema/v3.0/transaction_transfer.yaml
transactions/common/schema/v3.0/transaction_validator_election.yaml
transactions/common/schema/v3.0/transaction_vote.yaml
transactions/common/script.py
transactions/common/transaction.py
transactions/common/transaction_link.py
transactions/common/transaction_mode_types.py
transactions/common/utils.py
transactions/types/__init__.py
transactions/types/assets/__init__.py
transactions/types/assets/compose.py
transactions/types/assets/create.py
transactions/types/assets/decompose.py
transactions/types/assets/transfer.py
transactions/types/elections/__init__.py
transactions/types/elections/chain_migration_election.py
transactions/types/elections/election.py
transactions/types/elections/validator_election.py
transactions/types/elections/validator_utils.py
transactions/types/elections/vote.py
planetmint_transactions-0.8.2.dist-info/LICENSE
planetmint_transactions-0.8.2.dist-info/METADATA
planetmint_transactions-0.8.2.dist-info/WHEEL
planetmint_transactions-0.8.2.dist-info/RECORD
